slick_pay_django/__init__.py
slick_pay_django/admin.py
slick_pay_django/apps.py
slick_pay_django/forms.py
slick_pay_django/models.py
slick_pay_django/payment_manager.py
slick_pay_django/tests.py
slick_pay_django/utils.py
slick_pay_django/views.py
slick_pay_django/migrations/__init__.py
slick_pay_django/static/images/logo-checkout.png
slick_pay_django/static/images/logo-white-horizon.png
slick_pay_django/static/images/pay.webp
slick_pay_django/templates/slick_pay_django/_base.html
slick_pay_django/templates/slick_pay_django/fake-payment-view.html
slick_pay_django/templates/slick_pay_django/widgets/fake-payment-form.html
slickpay_django/__init__.py
slickpay_django/admin.py
slickpay_django/apps.py
slickpay_django/forms.py
slickpay_django/models.py
slickpay_django/payment_manager.py
slickpay_django/tests.py
slickpay_django/utils.py
slickpay_django/views.py
slickpay_django/migrations/__init__.py
slickpay_django/static/images/logo-checkout.png
slickpay_django/static/images/logo-white-horizon.png
slickpay_django/static/images/pay.webp
slickpay_django/templates/chargily_epay_django/_base.html
slickpay_django/templates/chargily_epay_django/fake-payment-view.html
slickpay_django/templates/chargily_epay_django/widgets/fake-payment-form.html
slickpay_django/templates/slickpay_django/_base.html
slickpay_django/templates/slickpay_django/fake-payment-view.html
slickpay_django/templates/slickpay_django/widgets/fake-payment-form.html
slick_pay_Django-2.1.dist-info/LICENSE
slick_pay_Django-2.1.dist-info/METADATA
slick_pay_Django-2.1.dist-info/WHEEL
slick_pay_Django-2.1.dist-info/top_level.txt
slick_pay_Django-2.1.dist-info/RECORD
